lygos/__init__.py
lygos/main.py
lygos/plot_tess_psfn.py
lygos/util.py
lygos-1.1.dist-info/LICENSE
lygos-1.1.dist-info/METADATA
lygos-1.1.dist-info/WHEEL
lygos-1.1.dist-info/top_level.txt
lygos-1.1.dist-info/RECORD
