Metadata-Version: 2.1
Name: lygos
Version: 1.1
Summary: PSF modeling of images in time domain astronomy
Home-page: https://github.com/tdaylan/lygos
Author: Tansu Daylan
Author-email: tansu.daylan@gmail.com
License: MIT
Download-URL: https://github.com/tdaylan/lygos
Platform: UNKNOWN
Classifier: Development Status :: 4 - Beta
Classifier: Intended Audience :: Science/Research
Classifier: License :: OSI Approved :: MIT License
Classifier: Programming Language :: Python
